{
	"attributes": {
		"minecraft:generic.max_health": {
			"every": 1,
			"amount": 0.04,
			"ceil": false,
			"percent": true,
			"exceptions": {
				"dimensions": [],
				"entities": [],
				"structures": [],
				"biomes": [],
				"mods": []
			}
		},
		"minecraft:generic.attack_damage": {
			"every": 1,
			"amount": 0.065,
			"ceil": false,
			"percent": true,
			"exceptions": {
				"dimensions": [],
				"entities": [],
				"structures": [],
				"biomes": [],
				"mods": []
			}
		},
		"minecraft:generic.movement_speed": {
			"every": 1,
			"amount": 0.001,
			"ceil": false,
			"percent": true,
			"exceptions": {
				"dimensions": [],
				"entities": [],
				"structures": [],
				"biomes": [],
				"mods": []
			}
		},
		"minecraft:generic.attack_knockback": {
			"every": 1,
			"amount": 0.08,
			"ceil": true,
			"percent": false,
			"exceptions": {
				"dimensions": [],
				"entities": [],
				"structures": [],
				"biomes": [],
				"mods": []
			}
		},
		"minecraft:generic.armor": {
			"every": 1,
			"amount": 0.5,
			"ceil": true,
			"percent": false,
			"exceptions": {
				"dimensions": [],
				"entities": [],
				"structures": [],
				"biomes": [],
				"mods": []
			}
		},
		"minecraft:generic.armor_toughness": {
			"every": 1,
			"amount": 0.25,
			"ceil": true,
			"percent": false,
			"exceptions": {
				"dimensions": [],
				"entities": [],
				"structures": [],
				"biomes": [],
				"mods": []
			}
		},
		"minecraft:generic.knockback_resistance": {
			"every": 1,
			"amount": 0.02,
			"ceil": true,
			"percent": false,
			"exceptions": {
				"dimensions": [],
				"entities": [],
				"structures": [],
				"biomes": [],
				"mods": []
			}
		},
		"irons_spellbooks:fire_magic_resist": {
			"every": 1,
			"amount": 0,
			"ceil": false,
			"percent": false,
			"exceptions": {
				"dimensions": [],
				"entities": [],
				"structures": [],
				"biomes": [],
				"mods": []
			}
		}
	},
	"leveling": {
		"maxLevel": 100,
		"baseXP": 150,
		"growthFactor": 1.085,
		"smoothing": 100,
		"curveModifier": 0.58,
		"minXP": 10,
		"round": true,
		"xp": {
			"baseValues": {
				"common": 6,
				"uncommon": 10,
				"elite": 15,
				"boss": 35
			},
			"playerLevelMultiplier": 0.04,
			"mobLevelMultiplier": 0.12,
			"dynamicScaling": {
				"enabled": true,
				"startLevel": 25,
				"baseDivider": 40,
				"exponent": 0.9
			},
			"randomize": true,
			"minXP": 1,
			"maxXP": 1500
		},
		"mobRarity": {
			"uncommon": [
				"minecraft:wither_skeleton",
				"minecraft:ghast"
			],
			"elite": [
				"minecraft:witch",
				"minecraft:piglin_brute",
				"minecraft:enderman"
			],
			"boss": [
				"minecraft:ender_dragon",
				"minecraft:wither",
				"minecraft:warden"
			]
		}
	},
	"debug": true,
	"calculatedLevels": {
		"1": 163,
		"2": 264,
		"3": 363,
		"4": 465,
		"5": 574,
		"6": 693,
		"7": 822,
		"8": 965,
		"9": 1122,
		"10": 1295,
		"11": 1487,
		"12": 1699,
		"13": 1935,
		"14": 2196,
		"15": 2486,
		"16": 2809,
		"17": 3166,
		"18": 3564,
		"19": 4006,
		"20": 4498,
		"21": 5045,
		"22": 5653,
		"23": 6331,
		"24": 7085,
		"25": 7925,
		"26": 8861,
		"27": 9904,
		"28": 11067,
		"29": 12365,
		"30": 13812,
		"31": 15428,
		"32": 17232,
		"33": 19247,
		"34": 21497,
		"35": 24013,
		"36": 26825,
		"37": 29970,
		"38": 33487,
		"39": 37423,
		"40": 41828,
		"41": 46760,
		"42": 52282,
		"43": 58467,
		"44": 65396,
		"45": 73159,
		"46": 81860,
		"47": 91612,
		"48": 102546,
		"49": 114804,
		"50": 128550,
		"51": 143967,
		"52": 161258,
		"53": 180654,
		"54": 202412,
		"55": 226821,
		"56": 254205,
		"57": 284929,
		"58": 319400,
		"59": 358075,
		"60": 401467,
		"61": 450151,
		"62": 504771,
		"63": 566048,
		"64": 634792,
		"65": 711907,
		"66": 798408,
		"67": 895431,
		"68": 1004247,
		"69": 1126279,
		"70": 1263120,
		"71": 1416552,
		"72": 1588570,
		"73": 1781402,
		"74": 1997543,
		"75": 2239782,
		"76": 2511235,
		"77": 2815388,
		"78": 3156133,
		"79": 3537822,
		"80": 3965313,
		"81": 4444036,
		"82": 4980052,
		"83": 5580127,
		"84": 6251818,
		"85": 7003555,
		"86": 7844749,
		"87": 8785895,
		"88": 9838706,
		"89": 11016241,
		"90": 12333066,
		"91": 13805418,
		"92": 15451398,
		"93": 17291183,
		"94": 19347254,
		"95": 21644661,
		"96": 24211309,
		"97": 27078279,
		"98": 30280183,
		"99": 33855560,
		"100": 37847316
	}
}