{
  "id": "skilltree:blacksmith_defensive_7",
  "bonuses": [
    {
      "type": "skilltree:attribute",
      "attribute": "minecraft:generic.armor",
      "id": "74d167f1-840d-46a3-bb94-2cc953509e1a",
      "name": "SkillBonus",
      "amount": 1.0,
      "operation": 0,
      "player_multiplier": {
        "type": "skilltree:none"
      },
      "player_condition": {
        "type": "skilltree:none"
      }
    }
  ],
  "directConnections": [],
  "longConnections": [],
  "oneWayConnections": [],
  "tags": [],
  "backgroundTexture": "skilltree:textures/icons/background/lesser.png",
  "iconTexture": "skilltree:textures/icons/blacksmith_defensive_1.png",
  "borderTexture": "skilltree:textures/tooltip/lesser.png",
  "titleColor": "",
  "positionX": -307.1785,
  "positionY": -115.01274,
  "buttonSize": 16,
  "isStartingPoint": false
}